mcp_server_discogs/__init__.py
mcp_server_discogs/__main__.py
mcp_server_discogs/server.py
mcp_server_discogs-0.2.0.dist-info/METADATA
mcp_server_discogs-0.2.0.dist-info/WHEEL
mcp_server_discogs-0.2.0.dist-info/entry_points.txt
mcp_server_discogs-0.2.0.dist-info/licenses/LICENSE
mcp_server_discogs-0.2.0.dist-info/RECORD
