Metadata-Version: 2.4
Name: mcp-server-discogs
Version: 0.2.0
Summary: An MCP Server to interact with the discogs API, supports read operations (for the moment)
Author-email: Konstantin Wolff <konstantin.bc@googlemail.com>
License-Expression: BSD-3-Clause
License-File: LICENSE
Classifier: Development Status :: 4 - Beta
Classifier: Intended Audience :: Developers
Classifier: Programming Language :: Python :: 3.12
Classifier: Programming Language :: Python :: 3.13
Classifier: Topic :: Utilities
Requires-Python: >=3.13
Requires-Dist: mcp[cli]>=1.6.0
Requires-Dist: mcpo>=0.0.13
Requires-Dist: python3-discogs-client>=2.8
